shrtcodes/__init__.py
shrtcodes/py.typed
shrtcodes-1.2.0.dist-info/LICENSE
shrtcodes-1.2.0.dist-info/METADATA
shrtcodes-1.2.0.dist-info/WHEEL
shrtcodes-1.2.0.dist-info/RECORD
