Metadata-Version: 2.1
Name: shrtcodes
Version: 1.2.0
Summary: Simple shortcodes for Python.
Home-page: https://github.com/Peter554/shrtcodes#readme
License: MIT
Author: Peter Byfield
Author-email: byfield554@gmail.com
Requires-Python: >=3.10,<4.0
Classifier: License :: OSI Approved :: MIT License
Classifier: Programming Language :: Python :: 3
Classifier: Programming Language :: Python :: 3.10
Classifier: Programming Language :: Python :: 3.11
Project-URL: Repository, https://github.com/Peter554/shrtcodes
